pmc_singleton-0.1.4-py3.8-nspkg.pth
pmc/singleton/__init__.py
pmc/singleton/main.py
pmc_singleton-0.1.4.dist-info/METADATA
pmc_singleton-0.1.4.dist-info/WHEEL
pmc_singleton-0.1.4.dist-info/namespace_packages.txt
pmc_singleton-0.1.4.dist-info/top_level.txt
pmc_singleton-0.1.4.dist-info/RECORD
