Metadata-Version: 2.1
Name: pmc-singleton
Version: 0.1.4
Summary: PMC package for singleton class decorator.
Home-page: https://github.com/kolotev/python-pmc-singleton
Maintainer: Andrei Kolotev
Maintainer-email: kolotev@gmail.com
License: Public Domain
Platform: UNKNOWN
Classifier: Development Status :: 4 - Beta
Classifier: Topic :: Software Development :: Libraries :: Python Modules
Classifier: License :: Public Domain
